pandas_ex/__init__.py
pandas_ex/core/__init__.py
pandas_ex/core/frame.py
pandas_ex/parallel/__init__.py
pandas_ex/parallel/_classes.py
pandas_ex-0.0.1.dist-info/LICENSE
pandas_ex-0.0.1.dist-info/METADATA
pandas_ex-0.0.1.dist-info/WHEEL
pandas_ex-0.0.1.dist-info/top_level.txt
pandas_ex-0.0.1.dist-info/RECORD
